COPYING.txt
MANIFEST.in
README.rst
setup.py
google/__init__.py
google/refine/__init__.py
google/refine/facet.py
google/refine/history.py
google/refine/refine.py
refine_client.egg-info/PKG-INFO
refine_client.egg-info/SOURCES.txt
refine_client.egg-info/dependency_links.txt
refine_client.egg-info/requires.txt
refine_client.egg-info/top_level.txt
tests/__init__.py
tests/refinetest.py
tests/test_facet.py
tests/test_history.py
tests/test_refine.py
tests/test_refine_small.py
tests/test_tutorial.py
tests/data/duplicates.csv
tests/data/eli-lilly.csv
tests/data/fixed-rows.csv
tests/data/louisiana-elected-officials.csv
tests/data/us_economic_assistance.csv
tests/data/variable-rows.csv