Metadata-Version: 1.0
Name: refine-client
Version: 0.2.1
Summary: The Google Refine Python Client Library provides an interface to communicating with a Google Refine server.
Home-page: https://github.com/PaulMakepeace/refine-client-py
Author: Paul Makepeace
Author-email: paulm@paulm.com
License: UNKNOWN
Platform: Any
Classifier: Development Status :: 3 - Alpha
Classifier: Intended Audience :: Developers
Classifier: License :: OSI Approved :: GNU General Public License (GPL)
Classifier: Operating System :: OS Independent
Classifier: Programming Language :: Python
Classifier: Topic :: Software Development :: Libraries :: Python Modules
Classifier: Topic :: Text Processing
